nestd/__init__.py
nestd-0.3.2.dist-info/WHEEL
nestd-0.3.2.dist-info/METADATA
nestd-0.3.2.dist-info/RECORD
